etc/bash_completion.d/linode-cli.sh
linodecli/__init__.py
linodecli/__main__.py
linodecli/api_request.py
linodecli/arg_helpers.py
linodecli/cli.py
linodecli/completion.py
linodecli/data-3
linodecli/helpers.py
linodecli/oauth-landing-page.html
linodecli/operation.py
linodecli/output.py
linodecli/response.py
linodecli/configuration/__init__.py
linodecli/configuration/auth.py
linodecli/configuration/helpers.py
linodecli/plugins/__init__.py
linodecli/plugins/firewall-editor.py
linodecli/plugins/image-upload.py
linodecli/plugins/ssh.py
linodecli/plugins/obj/__init__.py
linodecli/plugins/obj/config.py
linodecli/plugins/obj/helpers.py
linode_cli_testrelease-5.24.0.dist-info/LICENSE
linode_cli_testrelease-5.24.0.dist-info/METADATA
linode_cli_testrelease-5.24.0.dist-info/WHEEL
linode_cli_testrelease-5.24.0.dist-info/entry_points.txt
linode_cli_testrelease-5.24.0.dist-info/top_level.txt
linode_cli_testrelease-5.24.0.dist-info/RECORD
