Metadata-Version: 2.1
Name: linode-cli-testrelease
Version: 5.24.0
Summary: CLI for the Linode API
Home-page: https://www.linode.com/docs/api/
Author: Linode
Author-email: developers@linode.com
License: BSD 3-Clause License
Platform: UNKNOWN
Requires-Python: >=3.6
License-File: LICENSE
Requires-Dist: terminaltables
Requires-Dist: requests
Requires-Dist: PyYAML
